keyrings/__init__.py
keyrings/gauth.py
keyrings/google-artifactregistry-auth-py2/gauth.py
keyrings.google_artifactregistry_auth_py2-1.1.2.post7.dist-info/LICENSE
keyrings.google_artifactregistry_auth_py2-1.1.2.post7.dist-info/METADATA
keyrings.google_artifactregistry_auth_py2-1.1.2.post7.dist-info/WHEEL
keyrings.google_artifactregistry_auth_py2-1.1.2.post7.dist-info/entry_points.txt
keyrings.google_artifactregistry_auth_py2-1.1.2.post7.dist-info/top_level.txt
keyrings.google_artifactregistry_auth_py2-1.1.2.post7.dist-info/RECORD
