Metadata-Version: 2.1
Name: keyrings.google-artifactregistry-auth-py2
Version: 1.1.2.post7
Summary: Keyring backend for Google Auth tokens - a fork for Python 2
Home-page: UNKNOWN
Author: Megan Kuo
Author-email: megankuo@google.com
License: UNKNOWN
Platform: UNKNOWN
Classifier: Development Status :: 5 - Production/Stable
Classifier: Intended Audience :: Developers
Classifier: License :: OSI Approved :: Apache Software License
Classifier: Programming Language :: Python :: 2
Requires-Python: >=2.7
Requires-Dist: keyring (<19.0.0)
Requires-Dist: google-auth (<2)
Requires-Dist: requests (<2.28)
Requires-Dist: pluggy (<2)
Requires-Dist: cachetools (<4)
Requires-Dist: entrypoints (<0.4)
Requires-Dist: cryptography (<3.4)
Requires-Dist: setuptools (<45)
